{"nodes": [{"id": "users_bbarton_go_modules_prism_internal_cli_skill_go", "label": "skill.go", "file_type": "code", "source_file": "internal/cli/skill.go", "source_location": "L1"}, {"id": "cli_skill_newskillcmd", "label": "newSkillCmd()", "file_type": "code", "source_file": "internal/cli/skill.go", "source_location": "L16"}, {"id": "command", "label": "Command", "file_type": "code", "source_file": "internal/cli/skill.go", "source_location": "L16"}, {"id": "cli_skill_newskilllintcmd", "label": "newSkillLintCmd()", "file_type": "code", "source_file": "internal/cli/skill.go", "source_location": "L27"}, {"id": "cli_skill_newskilltestcmd", "label": "newSkillTestCmd()", "file_type": "code", "source_file": "internal/cli/skill.go", "source_location": "L39"}, {"id": "cli_skill_newskillbenchmarkcmd", "label": "newSkillBenchmarkCmd()", "file_type": "code", "source_file": "internal/cli/skill.go", "source_location": "L66"}, {"id": "cli_skillresult", "label": "skillResult", "file_type": "code", "source_file": "internal/cli/skill.go", "source_location": "L87"}, {"id": "cli_skill_lintskills", "label": "lintSkills()", "file_type": "code", "source_file": "internal/cli/skill.go", "source_location": "L96"}, {"id": "cli_skill_printskillresults", "label": "printSkillResults()", "file_type": "code", "source_file": "internal/cli/skill.go", "source_location": "L140"}, {"id": "cli_globalflags", "label": "globalFlags", "file_type": "code", "source_file": "internal/cli/skill.go", "source_location": "L171"}, {"id": "cli_globalflags_skillsdirordefault", "label": ".skillsDirOrDefault()", "file_type": "code", "source_file": "internal/cli/skill.go", "source_location": "L171"}, {"id": "cli_skill_fileexists", "label": "fileExists()", "file_type": "code", "source_file": "internal/cli/skill.go", "source_location": "L178"}], "edges": [{"source": "users_bbarton_go_modules_prism_internal_cli_skill_go", "target": "go_pkg_encoding_json", "relation": "imports_from", "confidence": "EXTRACTED", "source_file": "internal/cli/skill.go", "source_location": "L4", "weight": 1.0, "context": "import"}, {"source": "users_bbarton_go_modules_prism_internal_cli_skill_go", "target": "go_pkg_fmt", "relation": "imports_from", "confidence": "EXTRACTED", "source_file": "internal/cli/skill.go", "source_location": "L5", "weight": 1.0, "context": "import"}, {"source": "users_bbarton_go_modules_prism_internal_cli_skill_go", "target": "go_pkg_io_fs", "relation": "imports_from", "confidence": "EXTRACTED", "source_file": "internal/cli/skill.go", "source_location": "L6", "weight": 1.0, "context": "import"}, {"source": "users_bbarton_go_modules_prism_internal_cli_skill_go", "target": "go_pkg_os", "relation": "imports_from", "confidence": "EXTRACTED", "source_file": "internal/cli/skill.go", "source_location": "L7", "weight": 1.0, "context": "import"}, {"source": "users_bbarton_go_modules_prism_internal_cli_skill_go", "target": "go_pkg_path_filepath", "relation": "imports_from", "confidence": "EXTRACTED", "source_file": "internal/cli/skill.go", "source_location": "L8", "weight": 1.0, "context": "import"}, {"source": "users_bbarton_go_modules_prism_internal_cli_skill_go", "target": "go_pkg_strings", "relation": "imports_from", "confidence": "EXTRACTED", "source_file": "internal/cli/skill.go", "source_location": "L9", "weight": 1.0, "context": "import"}, {"source": "users_bbarton_go_modules_prism_internal_cli_skill_go", "target": "go_pkg_github_com_spf13_cobra", "relation": "imports_from", "confidence": "EXTRACTED", "source_file": "internal/cli/skill.go", "source_location": "L11", "weight": 1.0, "context": "import"}, {"source": "users_bbarton_go_modules_prism_internal_cli_skill_go", "target": "go_pkg_github_com_bryanbarton525_prism_internal_skill", "relation": "imports_from", "confidence": "EXTRACTED", "source_file": "internal/cli/skill.go", "source_location": "L13", "weight": 1.0, "context": "import"}, {"source": "users_bbarton_go_modules_prism_internal_cli_skill_go", "target": "cli_skill_newskillcmd", "relation": "contains", "confidence": "EXTRACTED", "source_file": "internal/cli/skill.go", "source_location": "L16", "weight": 1.0}, {"source": "cli_skill_newskillcmd", "target": "command", "relation": "references", "confidence": "EXTRACTED", "source_file": "internal/cli/skill.go", "source_location": "L16", "weight": 1.0, "context": "return_type"}, {"source": "users_bbarton_go_modules_prism_internal_cli_skill_go", "target": "cli_skill_newskilllintcmd", "relation": "contains", "confidence": "EXTRACTED", "source_file": "internal/cli/skill.go", "source_location": "L27", "weight": 1.0}, {"source": "cli_skill_newskilllintcmd", "target": "command", "relation": "references", "confidence": "EXTRACTED", "source_file": "internal/cli/skill.go", "source_location": "L27", "weight": 1.0, "context": "return_type"}, {"source": "users_bbarton_go_modules_prism_internal_cli_skill_go", "target": "cli_skill_newskilltestcmd", "relation": "contains", "confidence": "EXTRACTED", "source_file": "internal/cli/skill.go", "source_location": "L39", "weight": 1.0}, {"source": "cli_skill_newskilltestcmd", "target": "command", "relation": "references", "confidence": "EXTRACTED", "source_file": "internal/cli/skill.go", "source_location": "L39", "weight": 1.0, "context": "return_type"}, {"source": "users_bbarton_go_modules_prism_internal_cli_skill_go", "target": "cli_skill_newskillbenchmarkcmd", "relation": "contains", "confidence": "EXTRACTED", "source_file": "internal/cli/skill.go", "source_location": "L66", "weight": 1.0}, {"source": "cli_skill_newskillbenchmarkcmd", "target": "command", "relation": "references", "confidence": "EXTRACTED", "source_file": "internal/cli/skill.go", "source_location": "L66", "weight": 1.0, "context": "return_type"}, {"source": "users_bbarton_go_modules_prism_internal_cli_skill_go", "target": "cli_skillresult", "relation": "contains", "confidence": "EXTRACTED", "source_file": "internal/cli/skill.go", "source_location": "L87", "weight": 1.0}, {"source": "users_bbarton_go_modules_prism_internal_cli_skill_go", "target": "cli_skill_lintskills", "relation": "contains", "confidence": "EXTRACTED", "source_file": "internal/cli/skill.go", "source_location": "L96", "weight": 1.0}, {"source": "cli_skill_lintskills", "target": "cli_skillresult", "relation": "references", "confidence": "EXTRACTED", "source_file": "internal/cli/skill.go", "source_location": "L96", "weight": 1.0, "context": "return_type"}, {"source": "users_bbarton_go_modules_prism_internal_cli_skill_go", "target": "cli_skill_printskillresults", "relation": "contains", "confidence": "EXTRACTED", "source_file": "internal/cli/skill.go", "source_location": "L140", "weight": 1.0}, {"source": "cli_skill_printskillresults", "target": "cli_skillresult", "relation": "references", "confidence": "EXTRACTED", "source_file": "internal/cli/skill.go", "source_location": "L140", "weight": 1.0, "context": "parameter_type"}, {"source": "cli_globalflags", "target": "cli_globalflags_skillsdirordefault", "relation": "method", "confidence": "EXTRACTED", "source_file": "internal/cli/skill.go", "source_location": "L171", "weight": 1.0}, {"source": "users_bbarton_go_modules_prism_internal_cli_skill_go", "target": "cli_skill_fileexists", "relation": "contains", "confidence": "EXTRACTED", "source_file": "internal/cli/skill.go", "source_location": "L178", "weight": 1.0}, {"source": "cli_skill_newskillcmd", "target": "cli_skill_newskilllintcmd", "relation": "calls", "context": "call", "confidence": "EXTRACTED", "source_file": "internal/cli/skill.go", "source_location": "L21", "weight": 1.0}, {"source": "cli_skill_newskillcmd", "target": "cli_skill_newskilltestcmd", "relation": "calls", "context": "call", "confidence": "EXTRACTED", "source_file": "internal/cli/skill.go", "source_location": "L22", "weight": 1.0}, {"source": "cli_skill_newskillcmd", "target": "cli_skill_newskillbenchmarkcmd", "relation": "calls", "context": "call", "confidence": "EXTRACTED", "source_file": "internal/cli/skill.go", "source_location": "L23", "weight": 1.0}, {"source": "cli_skill_newskilllintcmd", "target": "cli_skill_lintskills", "relation": "calls", "context": "call", "confidence": "EXTRACTED", "source_file": "internal/cli/skill.go", "source_location": "L33", "weight": 1.0}, {"source": "cli_skill_newskilllintcmd", "target": "cli_skill_printskillresults", "relation": "calls", "context": "call", "confidence": "EXTRACTED", "source_file": "internal/cli/skill.go", "source_location": "L34", "weight": 1.0}, {"source": "cli_skill_newskilltestcmd", "target": "cli_skill_lintskills", "relation": "calls", "context": "call", "confidence": "EXTRACTED", "source_file": "internal/cli/skill.go", "source_location": "L45", "weight": 1.0}, {"source": "cli_skill_newskilltestcmd", "target": "cli_skill_fileexists", "relation": "calls", "context": "call", "confidence": "EXTRACTED", "source_file": "internal/cli/skill.go", "source_location": "L50", "weight": 1.0}, {"source": "cli_skill_newskilltestcmd", "target": "cli_globalflags_skillsdirordefault", "relation": "calls", "context": "call", "confidence": "EXTRACTED", "source_file": "internal/cli/skill.go", "source_location": "L50", "weight": 1.0}, {"source": "cli_skill_newskilltestcmd", "target": "cli_skill_printskillresults", "relation": "calls", "context": "call", "confidence": "EXTRACTED", "source_file": "internal/cli/skill.go", "source_location": "L61", "weight": 1.0}, {"source": "cli_skill_newskillbenchmarkcmd", "target": "cli_skill_lintskills", "relation": "calls", "context": "call", "confidence": "EXTRACTED", "source_file": "internal/cli/skill.go", "source_location": "L73", "weight": 1.0}, {"source": "cli_skill_newskillbenchmarkcmd", "target": "cli_skill_printskillresults", "relation": "calls", "context": "call", "confidence": "EXTRACTED", "source_file": "internal/cli/skill.go", "source_location": "L80", "weight": 1.0}, {"source": "cli_skill_lintskills", "target": "cli_globalflags_skillsdirordefault", "relation": "calls", "context": "call", "confidence": "EXTRACTED", "source_file": "internal/cli/skill.go", "source_location": "L97", "weight": 1.0}], "raw_calls": [{"caller_nid": "cli_skill_newskillcmd", "callee": "AddCommand", "is_member_call": true, "source_file": "/Users/bbarton/go/modules/prism/internal/cli/skill.go", "source_location": "L21"}, {"caller_nid": "cli_skill_newskillcmd", "callee": "AddCommand", "is_member_call": true, "source_file": "/Users/bbarton/go/modules/prism/internal/cli/skill.go", "source_location": "L22"}, {"caller_nid": "cli_skill_newskillcmd", "callee": "AddCommand", "is_member_call": true, "source_file": "/Users/bbarton/go/modules/prism/internal/cli/skill.go", "source_location": "L23"}, {"caller_nid": "cli_skill_newskilllintcmd", "callee": "MaximumNArgs", "is_member_call": false, "source_file": "/Users/bbarton/go/modules/prism/internal/cli/skill.go", "source_location": "L31"}, {"caller_nid": "cli_skill_newskilltestcmd", "callee": "MaximumNArgs", "is_member_call": false, "source_file": "/Users/bbarton/go/modules/prism/internal/cli/skill.go", "source_location": "L43"}, {"caller_nid": "cli_skill_newskilltestcmd", "callee": "Join", "is_member_call": false, "source_file": "/Users/bbarton/go/modules/prism/internal/cli/skill.go", "source_location": "L50"}, {"caller_nid": "cli_skill_newskilltestcmd", "callee": "append", "is_member_call": false, "source_file": "/Users/bbarton/go/modules/prism/internal/cli/skill.go", "source_location": "L51"}, {"caller_nid": "cli_skill_newskilltestcmd", "callee": "ValidateEvals", "is_member_call": false, "source_file": "/Users/bbarton/go/modules/prism/internal/cli/skill.go", "source_location": "L53"}, {"caller_nid": "cli_skill_newskilltestcmd", "callee": "DirFS", "is_member_call": false, "source_file": "/Users/bbarton/go/modules/prism/internal/cli/skill.go", "source_location": "L53"}, {"caller_nid": "cli_skill_newskilltestcmd", "callee": "append", "is_member_call": false, "source_file": "/Users/bbarton/go/modules/prism/internal/cli/skill.go", "source_location": "L56"}, {"caller_nid": "cli_skill_newskillbenchmarkcmd", "callee": "MaximumNArgs", "is_member_call": false, "source_file": "/Users/bbarton/go/modules/prism/internal/cli/skill.go", "source_location": "L71"}, {"caller_nid": "cli_skill_newskillbenchmarkcmd", "callee": "append", "is_member_call": false, "source_file": "/Users/bbarton/go/modules/prism/internal/cli/skill.go", "source_location": "L77"}, {"caller_nid": "cli_skill_newskillbenchmarkcmd", "callee": "Sprintf", "is_member_call": false, "source_file": "/Users/bbarton/go/modules/prism/internal/cli/skill.go", "source_location": "L77"}, {"caller_nid": "cli_skill_newskillbenchmarkcmd", "callee": "IntVar", "is_member_call": true, "source_file": "/Users/bbarton/go/modules/prism/internal/cli/skill.go", "source_location": "L83"}, {"caller_nid": "cli_skill_newskillbenchmarkcmd", "callee": "Flags", "is_member_call": true, "source_file": "/Users/bbarton/go/modules/prism/internal/cli/skill.go", "source_location": "L83"}, {"caller_nid": "cli_skill_lintskills", "callee": "ReadDir", "is_member_call": false, "source_file": "/Users/bbarton/go/modules/prism/internal/cli/skill.go", "source_location": "L102"}, {"caller_nid": "cli_skill_lintskills", "callee": "IsDir", "is_member_call": true, "source_file": "/Users/bbarton/go/modules/prism/internal/cli/skill.go", "source_location": "L107"}, {"caller_nid": "cli_skill_lintskills", "callee": "append", "is_member_call": false, "source_file": "/Users/bbarton/go/modules/prism/internal/cli/skill.go", "source_location": "L108"}, {"caller_nid": "cli_skill_lintskills", "callee": "Name", "is_member_call": true, "source_file": "/Users/bbarton/go/modules/prism/internal/cli/skill.go", "source_location": "L108"}, {"caller_nid": "cli_skill_lintskills", "callee": "make", "is_member_call": false, "source_file": "/Users/bbarton/go/modules/prism/internal/cli/skill.go", "source_location": "L112"}, {"caller_nid": "cli_skill_lintskills", "callee": "DirFS", "is_member_call": false, "source_file": "/Users/bbarton/go/modules/prism/internal/cli/skill.go", "source_location": "L113"}, {"caller_nid": "cli_skill_lintskills", "callee": "ReadFile", "is_member_call": false, "source_file": "/Users/bbarton/go/modules/prism/internal/cli/skill.go", "source_location": "L116"}, {"caller_nid": "cli_skill_lintskills", "callee": "ToSlash", "is_member_call": false, "source_file": "/Users/bbarton/go/modules/prism/internal/cli/skill.go", "source_location": "L116"}, {"caller_nid": "cli_skill_lintskills", "callee": "Join", "is_member_call": false, "source_file": "/Users/bbarton/go/modules/prism/internal/cli/skill.go", "source_location": "L116"}, {"caller_nid": "cli_skill_lintskills", "callee": "append", "is_member_call": false, "source_file": "/Users/bbarton/go/modules/prism/internal/cli/skill.go", "source_location": "L119"}, {"caller_nid": "cli_skill_lintskills", "callee": "append", "is_member_call": false, "source_file": "/Users/bbarton/go/modules/prism/internal/cli/skill.go", "source_location": "L120"}, {"caller_nid": "cli_skill_lintskills", "callee": "LoadDir", "is_member_call": false, "source_file": "/Users/bbarton/go/modules/prism/internal/cli/skill.go", "source_location": "L124"}, {"caller_nid": "cli_skill_lintskills", "callee": "append", "is_member_call": false, "source_file": "/Users/bbarton/go/modules/prism/internal/cli/skill.go", "source_location": "L126"}, {"caller_nid": "cli_skill_lintskills", "callee": "ValidateStructure", "is_member_call": false, "source_file": "/Users/bbarton/go/modules/prism/internal/cli/skill.go", "source_location": "L128"}, {"caller_nid": "cli_skill_lintskills", "callee": "append", "is_member_call": false, "source_file": "/Users/bbarton/go/modules/prism/internal/cli/skill.go", "source_location": "L130"}, {"caller_nid": "cli_skill_lintskills", "callee": "Contains", "is_member_call": false, "source_file": "/Users/bbarton/go/modules/prism/internal/cli/skill.go", "source_location": "L132"}, {"caller_nid": "cli_skill_lintskills", "callee": "string", "is_member_call": false, "source_file": "/Users/bbarton/go/modules/prism/internal/cli/skill.go", "source_location": "L132"}, {"caller_nid": "cli_skill_lintskills", "callee": "append", "is_member_call": false, "source_file": "/Users/bbarton/go/modules/prism/internal/cli/skill.go", "source_location": "L133"}, {"caller_nid": "cli_skill_lintskills", "callee": "append", "is_member_call": false, "source_file": "/Users/bbarton/go/modules/prism/internal/cli/skill.go", "source_location": "L135"}, {"caller_nid": "cli_skill_printskillresults", "callee": "NewEncoder", "is_member_call": false, "source_file": "/Users/bbarton/go/modules/prism/internal/cli/skill.go", "source_location": "L142"}, {"caller_nid": "cli_skill_printskillresults", "callee": "SetIndent", "is_member_call": true, "source_file": "/Users/bbarton/go/modules/prism/internal/cli/skill.go", "source_location": "L143"}, {"caller_nid": "cli_skill_printskillresults", "callee": "Encode", "is_member_call": true, "source_file": "/Users/bbarton/go/modules/prism/internal/cli/skill.go", "source_location": "L144"}, {"caller_nid": "cli_skill_printskillresults", "callee": "Printf", "is_member_call": false, "source_file": "/Users/bbarton/go/modules/prism/internal/cli/skill.go", "source_location": "L154"}, {"caller_nid": "cli_skill_printskillresults", "callee": "Printf", "is_member_call": false, "source_file": "/Users/bbarton/go/modules/prism/internal/cli/skill.go", "source_location": "L156"}, {"caller_nid": "cli_skill_printskillresults", "callee": "Printf", "is_member_call": false, "source_file": "/Users/bbarton/go/modules/prism/internal/cli/skill.go", "source_location": "L159"}, {"caller_nid": "cli_skill_printskillresults", "callee": "Printf", "is_member_call": false, "source_file": "/Users/bbarton/go/modules/prism/internal/cli/skill.go", "source_location": "L162"}, {"caller_nid": "cli_skill_printskillresults", "callee": "Errorf", "is_member_call": false, "source_file": "/Users/bbarton/go/modules/prism/internal/cli/skill.go", "source_location": "L166"}, {"caller_nid": "cli_globalflags_skillsdirordefault", "callee": "Join", "is_member_call": false, "source_file": "/Users/bbarton/go/modules/prism/internal/cli/skill.go", "source_location": "L175"}, {"caller_nid": "cli_skill_fileexists", "callee": "Stat", "is_member_call": false, "source_file": "/Users/bbarton/go/modules/prism/internal/cli/skill.go", "source_location": "L179"}]}
