{"nodes": [{"id": "agents_github_cli_github_cli_agent", "label": "GitHub CLI Agent", "file_type": "document", "source_file": "agents/github-cli.md", "source_location": null, "source_url": null, "captured_at": null, "author": null, "contributor": null}, {"id": "agents_github_cli_evidence_backed_diagnostics", "label": "Evidence-backed GitHub Diagnostics", "file_type": "rationale", "source_file": "agents/github-cli.md", "source_location": null, "source_url": null, "captured_at": null, "author": null, "contributor": null, "rationale": "Repository diagnosis must cite attempted commands and concrete identifiers and must not claim write actions."}], "edges": [{"source": "agents_github_cli_github_cli_agent", "target": "agents_github_cli_evidence_backed_diagnostics", "relation": "implements", "confidence": "EXTRACTED", "confidence_score": 1.0, "source_file": "agents/github-cli.md", "source_location": null, "weight": 1.0}, {"source": "agents_github_cli_github_cli_agent", "target": "constitutions_github_cli_github_cli_constitution", "relation": "references", "confidence": "EXTRACTED", "confidence_score": 1.0, "source_file": "agents/github-cli.md", "source_location": null, "weight": 1.0}, {"source": "agents_github_cli_evidence_backed_diagnostics", "target": "constitutions_github_cli_read_only_repository_diagnostics", "relation": "semantically_similar_to", "confidence": "INFERRED", "confidence_score": 0.95, "source_file": "agents/github-cli.md", "source_location": null, "weight": 1.0}], "hyperedges": []}
